<?xml version="1.0" encoding="utf-8" ?><dwsync><file name="header-default-centered.css" server="jsunursing.businesscatalyst.com//" local="3538449918" remote="3545313158" Dst="-1" /><file name="header-default.css" server="jsunursing.businesscatalyst.com//" local="3538449918" remote="3545313158" Dst="-1" /><file name="header-v1.css" server="jsunursing.businesscatalyst.com//" local="3538449918" remote="3545313158" Dst="-1" /><file name="header-v2.css" server="jsunursing.businesscatalyst.com//" local="3538449918" remote="3545313159" Dst="-1" /><file name="header-v3.css" server="jsunursing.businesscatalyst.com//" local="3538449918" remote="3545313159" Dst="-1" /><file name="header-v4-centered-1.css" server="jsunursing.businesscatalyst.com//" local="3538449918" remote="3545313160" Dst="-1" /><file name="header-v4-centered.css" server="jsunursing.businesscatalyst.com//" local="3538449918" remote="3545313161" Dst="-1" /><file name="header-v4.css" server="jsunursing.businesscatalyst.com//" local="3538449918" remote="3545313161" Dst="-1" /><file name="header-v5.css" server="jsunursing.businesscatalyst.com//" local="3538449918" remote="3545313161" Dst="-1" /><file name="header-v6.css" server="jsunursing.businesscatalyst.com//" local="3538449918" remote="3545313162" Dst="-1" /><file name="header-v7.css" server="jsunursing.businesscatalyst.com//" local="3538449918" remote="3545313162" Dst="-1" /><file name="header-v8.css" server="jsunursing.businesscatalyst.com//" local="3538449918" remote="3545313162" Dst="-1" /></dwsync>